clockplot/__init__.py
clockplot/generate.py
clockplot/plot.py
clockplot/utils.py
ptoclockplot-0.0.1.dist-info/LICENSE
ptoclockplot-0.0.1.dist-info/METADATA
ptoclockplot-0.0.1.dist-info/WHEEL
ptoclockplot-0.0.1.dist-info/top_level.txt
ptoclockplot-0.0.1.dist-info/RECORD
