Metadata-Version: 2.1
Name: ptoclockplot
Version: 0.0.1
Summary: A package for plotting clusters in a simple "pseudo-temporal-ordering", like a clock face.
Home-page: https://github.com/emcramer/clockplot
Author: Eric Cramer
Author-email: eric.cramer@curie.fr
License: UNKNOWN
Platform: UNKNOWN
Classifier: Programming Language :: Python :: 3
Classifier: License :: OSI Approved :: MIT License
Classifier: Operating System :: OS Independent
